{
	"GuestDetails": {
		"EmailID": "skomma@coredatalabs.com",
		"FirstName": "Test",
		"LastName": "TumiLast",
		"AddressLine1": "10 Sumac Way",
		"AddressLine2": "Add",
		"TownCity": "ABBOTSFORD",
		"Region": "California",
		"PostCode": "V4X 1A5",
		"Phone": "12345678901",
		"ProductName": "Tag"
	},
	"CreditCardDetails": {
		"NameOnCard": "test",
		"CardNumber": "4111111111111111",
		"CVV": "123",
		"ExipryMonth": "04",
		"ExpiryYear": "2020",
		"EmailID": "skomma@coredatalabs.com",
		"Phone": "12345678901"
	},
	"Products": {
		"BackOrderProduct": "0484706D",
		"BackOrderSKUID": "013234CPT",
		"PreOrderProduct": "0484660D",
		"DonationProduct": "TUMISTJUDE250",
		"GlobalLocatorProduct": "1111301041",
		"PromoCode20": "FixedDollar20",
		"PromoCode30": "T30-D5L6-E4LR-WEDL",
		"KoreaSKUID": "0222389AT2",
		"GiftBoxSKU": "028TRK",
		"SKUID": "00171B",
		"TumiStudioSKUID": "0117474T999",
		"NoramlSKUID": "014757D",
		"BreadCrumbsTest": "022020D2",
		"ColorSwatches": "01084371193",
		"ColorSwatchesKr": "0228069HNT",
		"AirlineProduct": "022061D2",
		"OutOfStock": "0494796PST",   
		"PageNotFound": "017DH",
		"SmartGiftSKUID" : "022060D2"
	},
	"SocialNetworkDetails": {
	    "GoogleEmailID": "tumi.automation@gmail.com",
	    "GooglePassword": "tumi1234",
	    "GoogleRecoveryEmailID":"emptumi@gmail.com",
		"GmailEmailID": "emptumi@gmail.com",
		"GmailPassword": "tumi1234",
		"Password_login": "Tumi_8864",
		"InValidGoogleEmail": "Employee.tumi@gmail.com",
		"InValidGooglePassword": "tumi12",
		"InstaEmailID": "TumiUS",
		"InstaPassword": "tumi123",
		"InvalidInstaEmailID": "TumiUS",
		"InvalidInstaPassword": "tumi12",
		"EmailID": "Employee.tumi@gmail.com",
		"Password": "t1"
	},
	"ShippingCharges":{
	"UsStandardShippingCharge":"$0.00",
	"PriorityShippingCharge":"$25.00",
	"SecondDayShippingCahrge":"$15.00"
	},
	"VoucherCodeDetails": {
		"VoucherID": "T30-D5L6-E4LR-WEDL",
		"RecipientName": "Test",
		"SenderName": "User",
		"Message": "Hello Tumi",
		"GiftCardnumber": "7018525193950000020",
		"Pinnumber": "98779393",
		"AltGiftCardnumber": "7018525193950000038",
		"AltPinNumber": "56579075",
		"CAVoucherID": "T05-H29B-C7AL-XK31",
		"KRVoucherID": "K10-DRP6-ZTPS-MXSP"
	},
	"MonoGramDetails": {
		"FirstMonoInput": "1",
		"SecondMonoInput": "2",
		"ThirdMonoInput": "3"
	},
	"GuestOrders": {
		"ProductName": "tag",
		"SKUID": "022060D2",
		"FirstMonoInput": "1",
		"SecondMonoInput": "2",
		"ThirdMonoInput": "3",
		"CAPostCode": "V2S 8B7"
	},
	"RegisteredOrders": {
		"EmailID": "skomma@coredatalabs.com",
		"Password": "tumi1234",
		"EmailID1" : "Tumi0604190837@gmail.com",
		"Password1": "TumiiEcom@123456789",
		"SKUID": "022061D2"
	},
	"FailedOrder": {
		"SKUID": "014757D",
		"EmailID": "skara@coredatalabs.com",
		"NameOnCard": "test",
		"CardNumber": "41111111111111",
		"CVV": "123",
		"ExipryMonth": "04",
		"ExpiryYear": "2020",
		"Phone": "12345678901"
	},
	"BackOrderProduct": {
		"SKUID": "13234CPT",
		"BackSKUID":"01193891041"
	},
	"PreOrderProduct": {
		"SKUID": "028TRK"
	},
	"GlobalLocatorProduct": {
		"AddressLine1": "1 LEFEUVRE RD",
		"NoramlSKUID": "01166761041"
		
	},
	"DonationPurchase": {
		"NoramlSKUID": "TUMISTJUDE250"
	},
	"TumiIDPRoduct": {
		"SKUID": "0117474T999"
	},
	"OrderWithTwoProducts": {
		"SKUID": "051DH",
		"FirstName": "Test",
		"LastName": "TumiLast",
		"AddressLine1": "10 Sumac Way",
		"nextAddressLine1": "1001 6Th Ave",
		"AddressLine2": "Add",
		"TownCity": "ABBOTSFORD",
		"Region": "California",
		"PostCode": "V4X 1A5",
		"Phone": "12345678901",
		"shipment1": "Fairport NY 14450",
		"shipment2": "Albany GA 31701",
		"shipmentCA1": "ABBOTSFORD",
		"shipmentCA2": "HOPE, BC, V0X 1L4",
		"RecipientName": "Test",
		"SenderName": "User"
	},
	"CreditCardDetailsMultishipmnet": {
		"NameOnCard": "test",
		"CardNumber": "4111111111111111",
		"CVV": "123",
		"ExipryMonth": "04",
		"ExpiryYear": "2020",
		"EmailID": "skomma@coredatalabs.com",
		"Phone": "12345678901",
		"FirstName": "Test",
		"LastName": "TumiLast",
		"AddressLine1": "10 Sumac Way",
		"nextAddressLine1": "1001 6Th Ave",
		"AddressLine2": "Add",
		"TownCity": "ABBOTSFORD",
		"Region": "California",
		"CAPostCode": "V2S 8B6",
		"PostCode": "V4X 1A5"
	},
	"PayPalDeatils": {
		"EmailID": "test@tumi.com",
		"Password": "passw0rd"
	},
	"GuestDeatilsForKorea": {
		"FirstName": "Test",
		"LastName": "TumiLast",
		"AddressLine1": "siolute",
		"AddressLine2": "Add",
		"TownCity": "ABCD",
		"PostCode": "12345",
		"Phone": "021234567"
	},
	"TumiLogin": {
		"EmailID1": "skomma@coredatalabs.com",
		"Password1": "tumi1234",
		"EmailID" : "Tumi0604190837@gmail.com",
		"Password": "TumiiEcom@123456789"
	},
	"CreateAccount": {
		"EmailID": "Tumi",
		"Password": "TumiEcom@123456789",
		"ConfirmPassword": "TumiiEcom@123456789",
		"FirstName": "Tumi",
		"LastName": "Ecom"
		
	},
	"ExistingAccount": {
		"EmailID": "Tumi1301193945@gmail.com",
		"Password": "TumiiEcom@123456789"
	},
	"TumiStudio": {
		"SKUID": "0117474T999"
	},
	"OutOfStock": {
		"SKUID": "0494796PST",
		"KoreaSKUID": "0494796PST"
	},
	"VerifyPGPFilters": {
		"USurl": "https://www.hybris-stage2.tumi.com",
		"CAurl": "https://ca.hybris-stage2.tumi.com",
		"KRurl": "https://kr.hybris-stage2.tumi.com"
	},
	"Environments": {
		"stage2": "https://www.hybris-stage2.tumi.com/",
		"stage3": "https://www.hybris-stage3.tumi.com/",
		"prod": "https://www.tumi.com/",
		"akamaiS2": "https://www.stg-hybris-akamai.tumi.com"
	},
	"BrowserStack": {
		"remoteBrowser": "Chrome",
		"remoteBrowserVersion": "62.0",
		"remoteOS": "Windows",
		"remoteOsVersion": "10"
	},
	"AlternateOptions": {
		"AlternatePh": "9012345612",
		"AlternatePhKr": "021234888",
		"AlternativeCard": "5555555555554444"
	},
	"TumiTracer": {
		"TracerID": "11111111111111111111",
		"EmailID": "skomma@coredatalabs.com",
		"FirstName": "Test",
		"LastName": "TumiLast",
		"AddressLine1": "10 Sumac Way",
		"Phone": "12345678901",
		"TownCity":"Fairport",
		"CATownCity":"ABBOTSFORD",
		"ZipCode":"14450-3322",
		"CAZipcode":"V2S 8B7" 
		
	}
}

